plotex/__init__.py
plotex/main.py
plotex/configuration/__init__.py
plotex/configuration/configuration.py
plotex/plotsize/__init__.py
plotex/plotsize/figsize.py
plotex/plotting/bar.py
plotex/plotting/line.py
plotex/plotting/pie.py
plotex/plotting/scatter.py
plotex/utils/__init__.py
plotex/utils/general.py
plotex/utils/hashing.py
plotex/utils/plotting.py
plotex-0.0.15.dist-info/LICENSE
plotex-0.0.15.dist-info/METADATA
plotex-0.0.15.dist-info/WHEEL
plotex-0.0.15.dist-info/top_level.txt
plotex-0.0.15.dist-info/RECORD
